{
  "_note": "10 tech tree entries. cost = tech points needed. unlocks = unit ids that become available.",
  "techs": [
    { "id": "T_INFANTRY", "name": "Infantry Training", "cost": 30, "icon": "🪖", "desc": "Unlock Lv2 Militia and Soldier",        "unlocks": ["U001", "U002"] },
    { "id": "T_ENGINEER", "name": "Engineering",       "cost": 40, "icon": "🔧", "desc": "Unlock Lv2 Engineer; +5 city repair",   "unlocks": ["U006"], "buff": { "cityRepair": 5 } },
    { "id": "T_ARMOR",    "name": "Armor Tech",        "cost": 60, "icon": "🛡", "desc": "Unlock Lv2 Light Tank and Tank",        "unlocks": ["U011", "U012"] },
    { "id": "T_ROCKET",   "name": "Rocket Science",    "cost": 80, "icon": "🚀", "desc": "Unlock Lv2 Rocket Tank",                "unlocks": ["U015"] },
    { "id": "T_AVIATION", "name": "Aviation",          "cost": 70, "icon": "✈",  "desc": "Unlock Lv2 Fighter and Bomber",         "unlocks": ["U021", "U022"] },
    { "id": "T_RECON",    "name": "Recon",             "cost": 35, "icon": "🛸", "desc": "Unlock Lv2 Scout Plane; show supply",   "unlocks": ["U023"] },
    { "id": "T_NAVY",     "name": "Naval Academy",     "cost": 50, "icon": "⚓", "desc": "Unlock Lv2 Patrol Boat and Destroyer",  "unlocks": ["U031", "U033"] },
    { "id": "T_AMPHIB",   "name": "Amphibious Ops",    "cost": 60, "icon": "⛴", "desc": "Unlock Lv2 Landing Ship",                "unlocks": ["U039"] },
    { "id": "T_DEFENSE",  "name": "Homeland Defense",  "cost": 45, "icon": "🗼", "desc": "Unlock Lv2 AA Tower; +1 city DEF",      "unlocks": ["U047"], "buff": { "cityDef": 1 } },
    { "id": "T_NUKE",     "name": "Nuclear Project",   "cost": 200,"icon": "☢", "desc": "Build nukes; -5 stability everywhere",  "unlocks": ["U041"] }
  ]
}
